assets/CameraTrapExample.ipynb
assets/biolith.svg
biolith/__init__.py
biolith/benchmarks/occu_spoccupancy.py
biolith/evaluation/__init__.py
biolith/evaluation/deviance.py
biolith/evaluation/diagnostics.py
biolith/evaluation/log_likelihood.py
biolith/evaluation/lppd.py
biolith/evaluation/posterior_predictive_check.py
biolith/evaluation/residuals.py
biolith/evaluation/waic.py
biolith/models/__init__.py
biolith/models/occu.py
biolith/models/occu_cop.py
biolith/models/occu_cs.py
biolith/models/occu_rn.py
biolith/regression/__init__.py
biolith/regression/abstract.py
biolith/regression/bart.py
biolith/regression/linear.py
biolith/regression/mlp.py
biolith/utils/__init__.py
biolith/utils/data.py
biolith/utils/distributions.py
biolith/utils/fit.py
biolith/utils/grid_search.py
biolith/utils/misc.py
biolith/utils/modeling.py
biolith/utils/predict.py
biolith/utils/spatial.py
biolith-0.0.14.dist-info/licenses/LICENSE
docs/api.rst
docs/conf.py
docs/index.rst
scripts/check.sh
scripts/format.sh
scripts/install_precommit.sh
scripts/pre-commit
biolith-0.0.14.dist-info/METADATA
biolith-0.0.14.dist-info/WHEEL
biolith-0.0.14.dist-info/top_level.txt
biolith-0.0.14.dist-info/RECORD
