Metadata-Version: 2.4
Name: biolith
Version: 0.0.14
Summary: Bayesian Ecological Modeling in Python
Author-email: Timm Haucke <haucke@mit.edu>
License: MIT
Project-URL: Documentation, https://timm.haucke.xyz/biolith/
Project-URL: Source, https://github.com/timmh/biolith
Keywords: python,occupancy,numpyro,bayesian,ecology
Classifier: Development Status :: 3 - Alpha
Classifier: Intended Audience :: Science/Research
Classifier: Programming Language :: Python :: 3
Requires-Python: >=3.9
License-File: LICENSE
Requires-Dist: numpy>=2
Requires-Dist: pandas>=2
Requires-Dist: jax>=0.5.0
Requires-Dist: numpyro>=0.18.0
Requires-Dist: funsor>=0.4.5
Provides-Extra: cuda11
Requires-Dist: jax[cuda11]>=0.5.0; extra == "cuda11"
Provides-Extra: cuda12
Requires-Dist: jax[cuda12]>=0.5.0; extra == "cuda12"
Provides-Extra: cuda13
Requires-Dist: jax[cuda13]>=0.5.0; extra == "cuda13"
Provides-Extra: tpu
Requires-Dist: jax[tpu]>=0.5.0; extra == "tpu"
Provides-Extra: rocm
Requires-Dist: jax[rocm]>=0.5.0; extra == "rocm"
Provides-Extra: dev
Requires-Dist: black; extra == "dev"
Requires-Dist: isort; extra == "dev"
Requires-Dist: docformatter; extra == "dev"
Requires-Dist: pylint; extra == "dev"
Requires-Dist: pyright; extra == "dev"
Requires-Dist: sphinx; extra == "dev"
Requires-Dist: sphinx_rtd_theme; extra == "dev"
Requires-Dist: myst_parser; extra == "dev"
Dynamic: license-file
